pathpy/__about__.py
pathpy/__init__.py
pathpy/config.cfg
pathpy/algorithms/__init__.py
pathpy/algorithms/centralities.py
pathpy/algorithms/community_detection.py
pathpy/algorithms/components.py
pathpy/algorithms/matrices.py
pathpy/algorithms/shortest_paths.py
pathpy/algorithms/trees.py
pathpy/converters/__init__.py
pathpy/converters/to_paths.py
pathpy/core/__init__.py
pathpy/core/api.py
pathpy/core/edge.py
pathpy/core/network.py
pathpy/core/node.py
pathpy/core/path.py
pathpy/core/base/__init__.py
pathpy/core/base/attributes.py
pathpy/core/base/classes.py
pathpy/core/base/collecions.py
pathpy/generators/__init__.py
pathpy/generators/lattice.py
pathpy/generators/random_graphs.py
pathpy/io/__init__.py
pathpy/io/io.py
pathpy/io/csv/__init__.py
pathpy/io/csv/csv.py
pathpy/io/graphml/__init__.py
pathpy/io/graphml/graphml.py
pathpy/io/konect/__init__.py
pathpy/io/konect/konect.py
pathpy/io/sql/__init__.py
pathpy/io/sql/sql.py
pathpy/models/__init__.py
pathpy/models/api.py
pathpy/models/directed_acyclic_graph.py
pathpy/models/higher_order_network.py
pathpy/models/models.py
pathpy/models/multi_order_model.py
pathpy/models/null_model.py
pathpy/models/temporal_network.py
pathpy/processes/__init__.py
pathpy/processes/random_walk.py
pathpy/statistics/__init__.py
pathpy/statistics/clustering.py
pathpy/statistics/degrees.py
pathpy/statistics/likelihoods.py
pathpy/statistics/modularity.py
pathpy/statistics/subpaths.py
pathpy/tests/__init__.py
pathpy/tests/test_algorithms.py
pathpy/tests/test_attributes.py
pathpy/tests/test_dag.py
pathpy/tests/test_edge.py
pathpy/tests/test_higher_order_network.py
pathpy/tests/test_hyperedge.py
pathpy/tests/test_io.py
pathpy/tests/test_mulit_order_model.py
pathpy/tests/test_network.py
pathpy/tests/test_node.py
pathpy/tests/test_null_model.py
pathpy/tests/test_path.py
pathpy/tests/test_statistics.py
pathpy/tests/test_temporal_network.py
pathpy/utils/__init__.py
pathpy/utils/config.py
pathpy/utils/helper.py
pathpy/utils/logger.py
pathpy3-3.0.0a2.dist-info/LICENSE
pathpy3-3.0.0a2.dist-info/METADATA
pathpy3-3.0.0a2.dist-info/WHEEL
pathpy3-3.0.0a2.dist-info/top_level.txt
pathpy3-3.0.0a2.dist-info/RECORD
